maxim/__init__.py
maxim/expiring_key_value_store.py
maxim/filter_objects.py
maxim/maxim.py
maxim/scribe.py
maxim/types.py
maxim/version.py
maxim/apis/__init__.py
maxim/apis/maxim_apis.py
maxim/cache/__init__.py
maxim/cache/cache.py
maxim/cache/inMemory.py
maxim/dataset/__init__.py
maxim/dataset/dataset.py
maxim/decorators/__init__.py
maxim/decorators/generation.py
maxim/decorators/retrieval.py
maxim/decorators/span.py
maxim/decorators/tool_call.py
maxim/decorators/trace.py
maxim/decorators/langchain/__init__.py
maxim/decorators/langchain/langchain.py
maxim/evaluators/__init__.py
maxim/evaluators/base_evaluator.py
maxim/evaluators/utils.py
maxim/logger/__init__.py
maxim/logger/logger.py
maxim/logger/utils.py
maxim/logger/writer.py
maxim/logger/agno/__init__.py
maxim/logger/agno/client.py
maxim/logger/anthropic/__init__.py
maxim/logger/anthropic/client.py
maxim/logger/anthropic/message.py
maxim/logger/anthropic/stream_manager.py
maxim/logger/anthropic/utils.py
maxim/logger/bedrock/__init__.py
maxim/logger/bedrock/async_client.py
maxim/logger/bedrock/client.py
maxim/logger/bedrock/utils.py
maxim/logger/components/__init__.py
maxim/logger/components/attachment.py
maxim/logger/components/base.py
maxim/logger/components/error.py
maxim/logger/components/feedback.py
maxim/logger/components/generation.py
maxim/logger/components/retrieval.py
maxim/logger/components/session.py
maxim/logger/components/span.py
maxim/logger/components/tool_call.py
maxim/logger/components/trace.py
maxim/logger/components/types.py
maxim/logger/components/utils.py
maxim/logger/crewai/__init__.py
maxim/logger/crewai/client.py
maxim/logger/crewai/utils.py
maxim/logger/elevenlabs/__init__.py
maxim/logger/elevenlabs/client.py
maxim/logger/elevenlabs/utils.py
maxim/logger/fireworks/__init__.py
maxim/logger/fireworks/client.py
maxim/logger/fireworks/helpers.py
maxim/logger/fireworks/utils.py
maxim/logger/gemini/__init__.py
maxim/logger/gemini/async_client.py
maxim/logger/gemini/client.py
maxim_py-3.14.10.dist-info/licenses/LICENSE.txt
maxim_py-3.14.10.dist-info/METADATA
maxim_py-3.14.10.dist-info/WHEEL
maxim_py-3.14.10.dist-info/top_level.txt
maxim_py-3.14.10.dist-info/RECORD
