Metadata-Version: 2.4
Name: maxim-py
Version: 3.14.10
Summary: A package that allows you to use the Maxim Python Library to interact with the Maxim Platform.
Author-email: Maxim Engineering <eng@getmaxim.ai>
Keywords: python,prompts,logs,workflow,testing
Classifier: Intended Audience :: Developers
Classifier: Programming Language :: Python :: 3
Classifier: Operating System :: Unix
Classifier: Operating System :: MacOS :: MacOS X
Classifier: Operating System :: Microsoft :: Windows
Requires-Python: >=3.9.20
License-File: LICENSE.txt
Requires-Dist: typing-extensions
Requires-Dist: filetype
Requires-Dist: httpx>=0.28.1
Dynamic: license-file
